CHANGES.txt
LICENSE.txt
MANIFEST.in
README.txt
setup.py
PyMarkov.egg-info/PKG-INFO
PyMarkov.egg-info/SOURCES.txt
PyMarkov.egg-info/dependency_links.txt
PyMarkov.egg-info/top_level.txt
pymarkov/__init__.py
pymarkov/markov.py