Metadata-Version: 1.0
Name: PyMarkov
Version: 0.1.0
Summary: Markov Chains made easy
Home-page: http://pypi.python.org/pypi/PyMarkov/
Author: Slater Victoroff
Author-email: Slater.R.Victoroff@gmail.com
License: LICENSE.txt
Platform: UNKNOWN
